setup.py
src/mysql_dump.py
src/mysql_dump.egg-info/PKG-INFO
src/mysql_dump.egg-info/SOURCES.txt
src/mysql_dump.egg-info/dependency_links.txt
src/mysql_dump.egg-info/entry_points.txt
src/mysql_dump.egg-info/requires.txt
src/mysql_dump.egg-info/top_level.txt
src/mysql_dump.egg-info/zip-safe