Metadata-Version: 1.1
Name: mysql-dump
Version: 0.2.2
Summary: MySQL Dump System
Home-page: http://mysqldump.hive.pt
Author: Hive Solutions Lda.
Author-email: development@hive.pt
License: GNU General Public License (GPL), Version 3
Keywords: mysql dump database export
Platform: UNKNOWN
Classifier: Development Status :: 5 - Production/Stable
Classifier: Topic :: Utilities
Classifier: License :: OSI Approved :: GNU General Public License (GPL)
Classifier: Operating System :: OS Independent
Classifier: Programming Language :: Python
Classifier: Programming Language :: Python :: 2.6
Classifier: Programming Language :: Python :: 2.7
Classifier: Programming Language :: Python :: 3.0
Classifier: Programming Language :: Python :: 3.1
Classifier: Programming Language :: Python :: 3.2
Classifier: Programming Language :: Python :: 3.3
Classifier: Programming Language :: Python :: 3.4
